st_seqviz/__init__.py
st_seqviz/pyproject.toml
st_seqviz/frontend/build/index-hZX3EGPc.js
st_seqviz-0.1.2.dist-info/licenses/LICENSE
st_seqviz-0.1.2.dist-info/METADATA
st_seqviz-0.1.2.dist-info/WHEEL
st_seqviz-0.1.2.dist-info/top_level.txt
st_seqviz-0.1.2.dist-info/RECORD
