Metadata-Version: 2.4
Name: st-seqviz
Version: 0.1.2
Summary: DNA, RNA, and protein sequence viewer
Author-email: Ghiles Meddour <ghiles.meddour.b@gmail.com>
License-Expression: MIT
Project-URL: Repository, https://github.com/ghilesmeddour/st-seqviz
Project-URL: Documentation, https://github.com/ghilesmeddour/st-seqviz
Project-URL: Changelog, https://github.com/ghilesmeddour/st-seqviz/blob/main/CHANGELOG.md
Project-URL: Releases, https://github.com/ghilesmeddour/st-seqviz/releases
Requires-Python: >=3.10
License-File: LICENSE
Requires-Dist: streamlit>=1.52
Provides-Extra: demo
Requires-Dist: bio>=1.8.1; extra == "demo"
Provides-Extra: devel
Requires-Dist: wheel; extra == "devel"
Requires-Dist: pytest==7.4.0; extra == "devel"
Requires-Dist: playwright==1.48.0; extra == "devel"
Requires-Dist: requests==2.31.0; extra == "devel"
Requires-Dist: pytest-playwright-snapshot==1.0; extra == "devel"
Requires-Dist: pytest-rerunfailures==12.0; extra == "devel"
Dynamic: license-file
